{
  "title": "Spy",
  "description": "Detects and alerts you to the presence of nearby enemy players.",
  "image": "https://raw.githubusercontent.com/Litas-dev/Azeroth-Legacy-Addons-Mirror/main/spy/logo.jpg",
  "author": "Unknown",
  "source": {
    "type": "warperia",
    "url": "https://warperia.com/addon-wotlk/spy/"
  },
  "downloads": {
    "wotlk": "https://raw.githubusercontent.com/Litas-dev/Azeroth-Legacy-Addons-Mirror/main/spy/3.3.5.zip",
    "tbc": null,
    "classic": null
  },
  "downloadUrl": "https://raw.githubusercontent.com/Litas-dev/Azeroth-Legacy-Addons-Mirror/main/spy/3.3.5.zip"
}